MiniWordTools/__init__.py
MiniWordTools-0.1.0.dist-info/LICENSE.txt
MiniWordTools-0.1.0.dist-info/METADATA
MiniWordTools-0.1.0.dist-info/WHEEL
MiniWordTools-0.1.0.dist-info/top_level.txt
MiniWordTools-0.1.0.dist-info/RECORD
