Metadata-Version: 2.1
Name: MiniWordTools
Version: 0.1.0
Summary: A library with tools for strings
Home-page: https://github.com/Ajayff4/testing2
Author: Ying Liqian
Author-email: jamesylq@gmail.com
License: UNKNOWN
Platform: UNKNOWN
Classifier: Programming Language :: Python :: 3
Classifier: License :: OSI Approved :: MIT License
Classifier: Operating System :: OS Independent
Requires-Python: >=3.6
